dovi_helpers/.DS_Store
dovi_helpers/__init__.py
dovi_helpers/cli/__init__.py
dovi_helpers/cli/__main__.py
dovi_helpers/cli/commands/__init__.py
dovi_helpers/cli/commands/demux.py
dovi_helpers/cli/commands/info.py
dovi_helpers/cli/commands/mux.py
dovi_helpers/cli/commands/pipeline.py
dovi_helpers/helpers.py
dovi_helpers/initializers.py
dovi_helpers/models/__init__.py
dovi_helpers/models/data.py
dovi_helpers/models/info.py
dovi_helpers-0.1.0.dist-info/entry_points.txt
dovi_helpers-0.1.0.dist-info/WHEEL
dovi_helpers-0.1.0.dist-info/METADATA
dovi_helpers-0.1.0.dist-info/RECORD
