Metadata-Version: 2.1
Name: dovi-helpers
Version: 0.1.0
Summary: Command line interface for collection of scripts to convert MKV container into Dolby Vision 8.1 compatible MP4.
License: MIT
Author: Skyross
Author-email: skyross000@gmail.com
Requires-Python: >=3.9,<4.0
Classifier: License :: OSI Approved :: MIT License
Classifier: Programming Language :: Python :: 3
Classifier: Programming Language :: Python :: 3.9
Classifier: Programming Language :: Python :: 3.10
Requires-Dist: click
Requires-Dist: colorama
Requires-Dist: pydantic
Requires-Dist: structlog
